{
  "date": "2026-06-08",
  "hour": "07",
  "slot": "2026-06-08_07",
  "crawled_at": "2026-06-08 07:00:00",
  "total_articles": 384,
  "topics": [
    {
      "rank": 1,
      "keyword": "선관위",
      "count": 26,
      "representative_title": "李 \"신뢰 잃은 선관위, 존재 의미없어\"",
      "representative_link": "https://n.news.naver.com/article/009/0005690459?ntype=RANKING",
      "press": "매일경제",
      "related_articles": [
        {
          "title": "조수빈 전 KBS 아나운서 “선관위, 해체 아니라 분쇄돼야” 직격",
          "link": "https://n.news.naver.com/article/025/0003528513?ntype=RANKING",
          "press": "중앙일보"
        },
        {
          "title": "李 \"신뢰 잃은 선관위, 존재 의미없어\"",
          "link": "https://n.news.naver.com/article/009/0005690459?ntype=RANKING",
          "press": "매일경제"
        },
        {
          "title": "\"의심도 하면 안 되나\"…비와이, '선관위·부정선거' 저격",
          "link": "https://n.news.naver.com/article/015/0005295851?ntype=RANKING",
          "press": "한국경제"
        },
        {
          "title": "한동훈 “선거철만 되면 선관위 직원들 휴가·휴직자 수 급증…부실 선거 관리 지속되는 원인”",
          "link": "https://n.news.naver.com/article/087/0001197593?ntype=RANKING",
          "press": "강원일보"
        },
        {
          "title": "전국 187개 대학, 계속되는 대자보… \"'참정권 훼손' 선관위 개혁\"",
          "link": "https://n.news.naver.com/article/002/0002444263?ntype=RANKING",
          "press": "프레시안"
        }
      ],
      "related_titles": [
        "조수빈 전 KBS 아나운서 “선관위, 해체 아니라 분쇄돼야” 직격",
        "李 \"신뢰 잃은 선관위, 존재 의미없어\"",
        "\"의심도 하면 안 되나\"…비와이, '선관위·부정선거' 저격",
        "한동훈 “선거철만 되면 선관위 직원들 휴가·휴직자 수 급증…부실 선거 관리 지속되는 원인”",
        "전국 187개 대학, 계속되는 대자보… \"'참정권 훼손' 선관위 개혁\""
      ],
      "category": "정치"
    },
    {
      "rank": 2,
      "keyword": "대통령",
      "count": 26,
      "representative_title": "李대통령, 신임총리 후보자 한성숙 지명",
      "representative_link": "https://n.news.naver.com/article/050/0000107031?ntype=RANKING",
      "press": "한경비즈니스",
      "related_articles": [
        {
          "title": "이재명 대통령 차기 총리로 한성숙 중소벤처기업부 장관 지명…한명숙 이후 20여년 만의 여성 총리",
          "link": "https://n.news.naver.com/article/087/0001197558?ntype=RANKING",
          "press": "강원일보"
        },
        {
          "title": "이 대통령, “참정권 침해 깊은 유감, 수사 지시…국회 국정조사 추진해달라”",
          "link": "https://n.news.naver.com/article/056/0012195326?ntype=RANKING",
          "press": "KBS"
        },
        {
          "title": "이 대통령 \"중앙선관위에 대한 검경 합동수사 지시\"‥총리 \"고위직 물러나야\"",
          "link": "https://n.news.naver.com/article/214/0001503886?ntype=RANKING",
          "press": "MBC"
        },
        {
          "title": "李대통령, 선관위에 \"신뢰잃은 기관\"…합수본 투표지수사 지시",
          "link": "https://n.news.naver.com/article/001/0016124365?ntype=RANKING",
          "press": "연합뉴스"
        },
        {
          "title": "오세훈 “투표용지 부족은 대통령 책임” 공세…‘재선거 요구’는 거리두기",
          "link": "https://n.news.naver.com/article/028/0002808537?ntype=RANKING",
          "press": "한겨레"
        }
      ],
      "related_titles": [
        "이재명 대통령 차기 총리로 한성숙 중소벤처기업부 장관 지명…한명숙 이후 20여년 만의 여성 총리",
        "이 대통령, “참정권 침해 깊은 유감, 수사 지시…국회 국정조사 추진해달라”",
        "이 대통령 \"중앙선관위에 대한 검경 합동수사 지시\"‥총리 \"고위직 물러나야\"",
        "李대통령, 선관위에 \"신뢰잃은 기관\"…합수본 투표지수사 지시",
        "오세훈 “투표용지 부족은 대통령 책임” 공세…‘재선거 요구’는 거리두기"
      ],
      "category": "정치"
    },
    {
      "rank": 3,
      "keyword": "재선거",
      "count": 21,
      "representative_title": "잠실 개표소 봉쇄 사흘째…“전국적 재선거 필요”",
      "representative_link": "https://n.news.naver.com/article/056/0012195328?ntype=RANKING",
      "press": "KBS",
      "related_articles": [
        {
          "title": "'거취 표명' 요구 뭉개는 장동혁 \"국민이 원하는 건 재선거\"",
          "link": "https://n.news.naver.com/article/002/0002444258?ntype=RANKING",
          "press": "프레시안"
        },
        {
          "title": "잠실 개표소 봉쇄 사흘째…“전국적 재선거 필요”",
          "link": "https://n.news.naver.com/article/056/0012195328?ntype=RANKING",
          "press": "KBS"
        },
        {
          "title": "이준석, '재선거' 주장 장동혁에 \"오세훈 자리 내놓으라는 거냐\"",
          "link": "https://n.news.naver.com/article/214/0001503884?ntype=RANKING",
          "press": "MBC"
        },
        {
          "title": "재선거 현실성 있나? '법의 문턱' 높고 위자료는 100~200만 원",
          "link": "https://n.news.naver.com/article/214/0001503890?ntype=RANKING",
          "press": "MBC"
        },
        {
          "title": "\"태극기만 흔들자\"‥극우와 선 긋고 구호는 \"재선거\"",
          "link": "https://n.news.naver.com/article/214/0001503887?ntype=RANKING",
          "press": "MBC"
        }
      ],
      "related_titles": [
        "'거취 표명' 요구 뭉개는 장동혁 \"국민이 원하는 건 재선거\"",
        "잠실 개표소 봉쇄 사흘째…“전국적 재선거 필요”",
        "이준석, '재선거' 주장 장동혁에 \"오세훈 자리 내놓으라는 거냐\"",
        "재선거 현실성 있나? '법의 문턱' 높고 위자료는 100~200만 원",
        "\"태극기만 흔들자\"‥극우와 선 긋고 구호는 \"재선거\""
      ],
      "category": "정치"
    },
    {
      "rank": 4,
      "keyword": "젠슨",
      "count": 20,
      "representative_title": "젠슨 황 만나 조용히 실리 챙긴 경영자들",
      "representative_link": "https://n.news.naver.com/article/023/0003980695?ntype=RANKING",
      "press": "조선일보",
      "related_articles": [
        {
          "title": "젠슨 황 방한 스케쥴 의도는? …딸 매디슨의 치밀한 전략 있었다",
          "link": "https://n.news.naver.com/article/015/0005295828?ntype=RANKING",
          "press": "한국경제"
        },
        {
          "title": "젠슨 황 \"8일 삼성전자 전영현 만난다, 이재용 회장은 미국서 만났다\"",
          "link": "https://n.news.naver.com/article/469/0000935040?ntype=RANKING",
          "press": "한국일보"
        },
        {
          "title": "젠슨 황, 맥주 한잔에 '5만원 팁' 전광판 '댄스 타임'까지…한국 야구 제대로 즐겼다",
          "link": "https://n.news.naver.com/article/469/0000935031?ntype=RANKING",
          "press": "한국일보"
        },
        {
          "title": "젠슨 황 만나 조용히 실리 챙긴 경영자들",
          "link": "https://n.news.naver.com/article/023/0003980695?ntype=RANKING",
          "press": "조선일보"
        },
        {
          "title": "젠슨 황, 최태원·SK 사장단과 '2차 깐부회동'…공고한 파트너십 재확인",
          "link": "https://n.news.naver.com/article/586/0000130930?ntype=RANKING",
          "press": "시사저널"
        }
      ],
      "related_titles": [
        "젠슨 황 방한 스케쥴 의도는? …딸 매디슨의 치밀한 전략 있었다",
        "젠슨 황 \"8일 삼성전자 전영현 만난다, 이재용 회장은 미국서 만났다\"",
        "젠슨 황, 맥주 한잔에 '5만원 팁' 전광판 '댄스 타임'까지…한국 야구 제대로 즐겼다",
        "젠슨 황 만나 조용히 실리 챙긴 경영자들",
        "젠슨 황, 최태원·SK 사장단과 '2차 깐부회동'…공고한 파트너십 재확인"
      ],
      "category": "산업/테크"
    },
    {
      "rank": 5,
      "keyword": "한성숙",
      "count": 16,
      "representative_title": "2기 총리에 한성숙 지명…두 번째 여성 총리 탄생하나",
      "representative_link": "https://n.news.naver.com/article/057/0001952690?ntype=RANKING",
      "press": "MBN",
      "related_articles": [
        {
          "title": "국민의힘, '차기 총리' 한성숙 지명에 \"투표지 사태 국면 전환용\"",
          "link": "https://n.news.naver.com/article/002/0002444271?ntype=RANKING",
          "press": "프레시안"
        },
        {
          "title": "국무총리 후보자 한성숙…“AI 대전환과 ‘모두의 성장’ 이끌 적임자”",
          "link": "https://n.news.naver.com/article/056/0012195330?ntype=RANKING",
          "press": "KBS"
        },
        {
          "title": "새 국무총리 한성숙 '깜짝 인선'…야당선 '타이밍' 놓고 비판",
          "link": "https://n.news.naver.com/article/437/0000494903?ntype=RANKING",
          "press": "JTBC"
        },
        {
          "title": "정성호도 강훈식도 아니었다…李대통령의 실용주의 카드 '한성숙 총리'",
          "link": "https://n.news.naver.com/article/586/0000130932?ntype=RANKING",
          "press": "시사저널"
        },
        {
          "title": "강훈식·정성호 아닌 한성숙 이유는…짧은 임기 맡길 관리형 총리 적임",
          "link": "https://n.news.naver.com/article/366/0001170019?ntype=RANKING",
          "press": "조선비즈"
        }
      ],
      "related_titles": [
        "국민의힘, '차기 총리' 한성숙 지명에 \"투표지 사태 국면 전환용\"",
        "국무총리 후보자 한성숙…“AI 대전환과 ‘모두의 성장’ 이끌 적임자”",
        "새 국무총리 한성숙 '깜짝 인선'…야당선 '타이밍' 놓고 비판",
        "정성호도 강훈식도 아니었다…李대통령의 실용주의 카드 '한성숙 총리'",
        "강훈식·정성호 아닌 한성숙 이유는…짧은 임기 맡길 관리형 총리 적임"
      ],
      "category": "산업/테크"
    }
  ],
  "stock_topics": [
    {
      "rank": 1,
      "keyword": "환율",
      "count": 11,
      "representative_title": "[단독]달러 안 내놓는 기업들…환율 1560원 넘었다",
      "representative_link": "https://n.news.naver.com/article/011/0004628420?ntype=RANKING",
      "press": "서울경제",
      "related_articles": [
        {
          "title": "“하락 요인 안보인다”…美 금리 우려-외인 매도에 천장 뚫은 환율",
          "link": "https://n.news.naver.com/article/020/0003725118?ntype=RANKING",
          "press": "동아일보"
        },
        {
          "title": "\"태국 바트보다 못하다고?\"…1560원 찍은 원화, 무슨 일이[1500원 치솟는 환율]①",
          "link": "https://n.news.naver.com/article/277/0005772774?ntype=RANKING",
          "press": "아시아경제"
        },
        {
          "title": "외국인 팔자에 환율 '휘청'...2분기 평균 IMF 이후 '최고'",
          "link": "https://n.news.naver.com/article/052/0002363172?ntype=RANKING",
          "press": "YTN"
        },
        {
          "title": "야간에 1561원까지 치솟은 환율… 정부 “시장교란 행위 점검”",
          "link": "https://n.news.naver.com/article/005/0001853498?ntype=RANKING",
          "press": "국민일보"
        },
        {
          "title": "[단독]달러 안 내놓는 기업들…환율 1560원 넘었다",
          "link": "https://n.news.naver.com/article/011/0004628420?ntype=RANKING",
          "press": "서울경제"
        }
      ],
      "related_titles": [
        "“하락 요인 안보인다”…美 금리 우려-외인 매도에 천장 뚫은 환율",
        "\"태국 바트보다 못하다고?\"…1560원 찍은 원화, 무슨 일이[1500원 치솟는 환율]①",
        "외국인 팔자에 환율 '휘청'...2분기 평균 IMF 이후 '최고'",
        "야간에 1561원까지 치솟은 환율… 정부 “시장교란 행위 점검”",
        "[단독]달러 안 내놓는 기업들…환율 1560원 넘었다"
      ],
      "category": "주식/코인"
    },
    {
      "rank": 2,
      "keyword": "코스피",
      "count": 7,
      "representative_title": "‘검은 금요일’ 여파 언제까지… 코스피 덮친 ‘3대 악재’",
      "representative_link": "https://n.news.naver.com/article/005/0001853558?ntype=RANKING",
      "press": "국민일보",
      "related_articles": [
        {
          "title": "‘검은 금요일’ 여파 언제까지… 코스피 덮친 ‘3대 악재’",
          "link": "https://n.news.naver.com/article/005/0001853558?ntype=RANKING",
          "press": "국민일보"
        },
        {
          "title": "지수는 사상 최고치인데 내 주식은 왜…코스피, 대형주만 웃었다",
          "link": "https://n.news.naver.com/article/243/0000098792?ntype=RANKING",
          "press": "이코노미스트"
        },
        {
          "title": "코스피 8000 돌파하자 '빚투' 폭주…3일 만에 대출 1조원 증가",
          "link": "https://n.news.naver.com/article/243/0000098800?ntype=RANKING",
          "press": "이코노미스트"
        },
        {
          "title": "삼전닉스·KB금융 말고 다 바뀌었대…코스피 상위 10위 격변",
          "link": "https://n.news.naver.com/article/024/0000106071?ntype=RANKING",
          "press": "매경이코노미"
        },
        {
          "title": "스페이스X 상장 D-5…코스피, 자금 이탈 우려 속 반도체 모멘텀 주목",
          "link": "https://n.news.naver.com/article/138/0002230103?ntype=RANKING",
          "press": "디지털데일리"
        }
      ],
      "related_titles": [
        "‘검은 금요일’ 여파 언제까지… 코스피 덮친 ‘3대 악재’",
        "지수는 사상 최고치인데 내 주식은 왜…코스피, 대형주만 웃었다",
        "코스피 8000 돌파하자 '빚투' 폭주…3일 만에 대출 1조원 증가",
        "삼전닉스·KB금융 말고 다 바뀌었대…코스피 상위 10위 격변",
        "스페이스X 상장 D-5…코스피, 자금 이탈 우려 속 반도체 모멘텀 주목"
      ],
      "category": "주식/코인"
    },
    {
      "rank": 3,
      "keyword": "달러",
      "count": 5,
      "representative_title": "'사상최대' 스페이스X 기업공개…청약자금 벌써 1500억 달러",
      "representative_link": "https://n.news.naver.com/article/079/0004155129?ntype=RANKING",
      "press": "노컷뉴스",
      "related_articles": [
        {
          "title": "'사상최대' 스페이스X 기업공개…청약자금 벌써 1500억 달러",
          "link": "https://n.news.naver.com/article/079/0004155129?ntype=RANKING",
          "press": "노컷뉴스"
        },
        {
          "title": "원/달러 1560원에 칼 빼든 외환당국…\"투기거래 엄정 조치\" 경고",
          "link": "https://n.news.naver.com/article/417/0001146475?ntype=RANKING",
          "press": "동행미디어 시대"
        },
        {
          "title": "유가 160달러, 산업 붕괴… '석유 재고' 지금처럼 줄면 벌어질 일 [주말 Q&A]",
          "link": "https://n.news.naver.com/article/665/0000007509?ntype=RANKING",
          "press": "더스쿠프"
        },
        {
          "title": "'사상최대' 스페이스X 기업공개…청약자금 벌써 1500억 달러",
          "link": "https://n.news.naver.com/article/079/0004155129?ntype=RANKING",
          "press": "노컷뉴스"
        },
        {
          "title": "원/달러 1560원에 칼 빼든 외환당국…\"투기거래 엄정 조치\" 경고",
          "link": "https://n.news.naver.com/article/417/0001146475?ntype=RANKING",
          "press": "동행미디어 시대"
        }
      ],
      "related_titles": [
        "'사상최대' 스페이스X 기업공개…청약자금 벌써 1500억 달러",
        "원/달러 1560원에 칼 빼든 외환당국…\"투기거래 엄정 조치\" 경고",
        "유가 160달러, 산업 붕괴… '석유 재고' 지금처럼 줄면 벌어질 일 [주말 Q&A]",
        "'사상최대' 스페이스X 기업공개…청약자금 벌써 1500억 달러",
        "원/달러 1560원에 칼 빼든 외환당국…\"투기거래 엄정 조치\" 경고"
      ],
      "category": "주식/코인"
    },
    {
      "rank": 4,
      "keyword": "엔비디아",
      "count": 4,
      "representative_title": "\"진짜 깐부\" SK 최태원·엔비디아 젠슨 황, 일주일 4번 회동[현장+]",
      "representative_link": "https://n.news.naver.com/article/293/0000085907?ntype=RANKING",
      "press": "블로터",
      "related_articles": [
        {
          "title": "깐부 회동 중 \"More HBM!\" 외쳤다…SK-엔비디아 'AI 협력' 발표 예고",
          "link": "https://n.news.naver.com/article/008/0005368209?ntype=RANKING",
          "press": "머니투데이"
        },
        {
          "title": "\"진짜 깐부\" SK 최태원·엔비디아 젠슨 황, 일주일 4번 회동[현장+]",
          "link": "https://n.news.naver.com/article/293/0000085907?ntype=RANKING",
          "press": "블로터"
        },
        {
          "title": "[속보] 젠슨 황-최태원, 8일 오전 'SK-엔비디아' 협업 계획 직접 미디어 발표 예정",
          "link": "https://n.news.naver.com/article/003/0013991976?ntype=RANKING",
          "press": "뉴시스"
        },
        {
          "title": "야구장 찾은 젠슨황 \"치맥보다 좋은 건 없다\"…엔비디아, 치킨 113마리 배달주문",
          "link": "https://n.news.naver.com/article/448/0000617572?ntype=RANKING",
          "press": "TV조선"
        },
        {
          "title": "깐부 회동 중 \"More HBM!\" 외쳤다…SK-엔비디아 'AI 협력' 발표 예고",
          "link": "https://n.news.naver.com/article/008/0005368209?ntype=RANKING",
          "press": "머니투데이"
        }
      ],
      "related_titles": [
        "깐부 회동 중 \"More HBM!\" 외쳤다…SK-엔비디아 'AI 협력' 발표 예고",
        "\"진짜 깐부\" SK 최태원·엔비디아 젠슨 황, 일주일 4번 회동[현장+]",
        "[속보] 젠슨 황-최태원, 8일 오전 'SK-엔비디아' 협업 계획 직접 미디어 발표 예정",
        "야구장 찾은 젠슨황 \"치맥보다 좋은 건 없다\"…엔비디아, 치킨 113마리 배달주문",
        "깐부 회동 중 \"More HBM!\" 외쳤다…SK-엔비디아 'AI 협력' 발표 예고"
      ],
      "category": "주식/코인"
    },
    {
      "rank": 5,
      "keyword": "젠슨",
      "count": 4,
      "representative_title": "젠슨 황 \"8일 삼성전자 전영현 만난다, 이재용 회장은 미국서 만났다\"",
      "representative_link": "https://n.news.naver.com/article/469/0000935040?ntype=RANKING",
      "press": "한국일보",
      "related_articles": [
        {
          "title": "젠슨 황 \"8일 삼성전자 전영현 만난다, 이재용 회장은 미국서 만났다\"",
          "link": "https://n.news.naver.com/article/469/0000935040?ntype=RANKING",
          "press": "한국일보"
        },
        {
          "title": "“친구들과 일한다”…최태원과 치맥한 젠슨 황, 다음 행선지는 삼성·네이버",
          "link": "https://n.news.naver.com/article/366/0001170043?ntype=RANKING",
          "press": "조선비즈"
        },
        {
          "title": "젠슨 황 \"8일 삼성전자 전영현 만난다, 이재용 회장은 미국서 만났다\"",
          "link": "https://n.news.naver.com/article/469/0000935040?ntype=RANKING",
          "press": "한국일보"
        },
        {
          "title": "“친구들과 일한다”…최태원과 치맥한 젠슨 황, 다음 행선지는 삼성·네이버",
          "link": "https://n.news.naver.com/article/366/0001170043?ntype=RANKING",
          "press": "조선비즈"
        },
        {
          "title": "젠슨 황 \"8일 삼성전자 전영현 만난다, 이재용 회장은 미국서 만났다\"",
          "link": "https://n.news.naver.com/article/469/0000935040?ntype=RANKING",
          "press": "한국일보"
        }
      ],
      "related_titles": [
        "젠슨 황 \"8일 삼성전자 전영현 만난다, 이재용 회장은 미국서 만났다\"",
        "“친구들과 일한다”…최태원과 치맥한 젠슨 황, 다음 행선지는 삼성·네이버",
        "젠슨 황 \"8일 삼성전자 전영현 만난다, 이재용 회장은 미국서 만났다\"",
        "“친구들과 일한다”…최태원과 치맥한 젠슨 황, 다음 행선지는 삼성·네이버",
        "젠슨 황 \"8일 삼성전자 전영현 만난다, 이재용 회장은 미국서 만났다\""
      ],
      "category": "주식/코인"
    }
  ],
  "moljak_topics": [
    {
      "rank": 1,
      "keyword": "대통령을",
      "series_title": "대통령을의 몰락",
      "count": 1,
      "representative_title": "21살 가발공장 노동자, 어떻게 대통령을 몰락시켰나 [김종성의 '히, 스토리']",
      "representative_link": "https://news.google.com/rss/articles/CBMiT0FVX3lxTFBILUl5Y0RfMTd4RXZGcnFuTWpjekdKMEs0a1RNMkl0Zkp4eE9CSjBUcUlFUFRlcl96ZE5xSXRUcmZBaVhDVWNBWW5yNXVhRlk?oc=5",
      "press": "",
      "related_articles": [
        {
          "title": "21살 가발공장 노동자, 어떻게 대통령을 몰락시켰나 [김종성의 '히, 스토리']",
          "link": "https://news.google.com/rss/articles/CBMiT0FVX3lxTFBILUl5Y0RfMTd4RXZGcnFuTWpjekdKMEs0a1RNMkl0Zkp4eE9CSjBUcUlFUFRlcl96ZE5xSXRUcmZBaVhDVWNBWW5yNXVhRlk?oc=5",
          "press": ""
        }
      ],
      "related_titles": [
        "21살 가발공장 노동자, 어떻게 대통령을 몰락시켰나 [김종성의 '히, 스토리']"
      ],
      "category": "몰락"
    },
    {
      "rank": 2,
      "keyword": "정치",
      "series_title": "정치의 몰락",
      "count": 1,
      "representative_title": "삭발 정치의 몰락···선거는 패하고 휑한 머리만 남았다",
      "representative_link": "https://news.google.com/rss/articles/CBMiXkFVX3lxTFBRb091eXRGdGVuX2dpVEl2QzRKUDRFdmFTcEZaTW1yaDNoVWVlR2ZLQWhGYWViUnZSWFZsQWV5QktRZHVheU41dWg0ZWtkSWN3d0ZWR1NxcHl4RUpyUUE?oc=5",
      "press": "",
      "related_articles": [
        {
          "title": "삭발 정치의 몰락···선거는 패하고 휑한 머리만 남았다",
          "link": "https://news.google.com/rss/articles/CBMiXkFVX3lxTFBRb091eXRGdGVuX2dpVEl2QzRKUDRFdmFTcEZaTW1yaDNoVWVlR2ZLQWhGYWViUnZSWFZsQWV5QktRZHVheU41dWg0ZWtkSWN3d0ZWR1NxcHl4RUpyUUE?oc=5",
          "press": ""
        }
      ],
      "related_titles": [
        "삭발 정치의 몰락···선거는 패하고 휑한 머리만 남았다"
      ],
      "category": "몰락"
    },
    {
      "rank": 3,
      "keyword": "일본",
      "series_title": "일본의 몰락",
      "count": 1,
      "representative_title": "[신장섭의 기업과 경제] 반도체, 일본의 몰락과 중국의 추격",
      "representative_link": "https://news.google.com/rss/articles/CBMiU0FVX3lxTFBfRTNpQkpoX1BfU0EzZXowd3UtTTYycWR1M2Z6ckExOEdmWGI2Qi1LOE9uZ3pCLW1GY2s0UWFacHhpTmlJcXNNeGR0akI5VVg3czUw?oc=5",
      "press": "",
      "related_articles": [
        {
          "title": "[신장섭의 기업과 경제] 반도체, 일본의 몰락과 중국의 추격",
          "link": "https://news.google.com/rss/articles/CBMiU0FVX3lxTFBfRTNpQkpoX1BfU0EzZXowd3UtTTYycWR1M2Z6ckExOEdmWGI2Qi1LOE9uZ3pCLW1GY2s0UWFacHhpTmlJcXNNeGR0akI5VVg3czUw?oc=5",
          "press": ""
        }
      ],
      "related_titles": [
        "[신장섭의 기업과 경제] 반도체, 일본의 몰락과 중국의 추격"
      ],
      "category": "몰락"
    },
    {
      "rank": 4,
      "keyword": "후보",
      "series_title": "후보의 몰락",
      "count": 1,
      "representative_title": "서울·평택·부산 북갑까지 '명픽 후보' 몰락 … 민심 李 정권에 사실상 회초리",
      "representative_link": "https://news.google.com/rss/articles/CBMie0FVX3lxTE96dmpnZ1VjWk9xQTRrQjZFODRJVFZiT1NCLV9BUzJtdC1mbDRnQy14NWkxZHpVMFNJc2Z6UEtQc0FBSVIxRkt5eHI1cjh5SlhtWUtwa2NMb3kyNkt0SmsxVlY0X2dUZXhJX3ExSVFheDVDMWtMREVYakVGQQ?oc=5",
      "press": "",
      "related_articles": [
        {
          "title": "서울·평택·부산 북갑까지 '명픽 후보' 몰락 … 민심 李 정권에 사실상 회초리",
          "link": "https://news.google.com/rss/articles/CBMie0FVX3lxTE96dmpnZ1VjWk9xQTRrQjZFODRJVFZiT1NCLV9BUzJtdC1mbDRnQy14NWkxZHpVMFNJc2Z6UEtQc0FBSVIxRkt5eHI1cjh5SlhtWUtwa2NMb3kyNkt0SmsxVlY0X2dUZXhJX3ExSVFheDVDMWtMREVYakVGQQ?oc=5",
          "press": ""
        }
      ],
      "related_titles": [
        "서울·평택·부산 북갑까지 '명픽 후보' 몰락 … 민심 李 정권에 사실상 회초리"
      ],
      "category": "몰락"
    },
    {
      "rank": 5,
      "keyword": "도그마",
      "series_title": "도그마의 몰락",
      "count": 1,
      "representative_title": "[배학수의 문화풍경] 도그마의 몰락",
      "representative_link": "https://news.google.com/rss/articles/CBMidEFVX3lxTE1qTDdIQkJ6WVpDbEFqN2J5ZllKVGhfMEdzeXBON2FNbkRkYTUxdUJMUlZpd2ZqV0djYXZIbzN6OHVmcDh1X0xmeGppNmhuWmJhanlORzluWjdKNDZoNTk1QWtGSVZOUldsdEljaFRNdjd4T0c1?oc=5",
      "press": "",
      "related_articles": [
        {
          "title": "[배학수의 문화풍경] 도그마의 몰락",
          "link": "https://news.google.com/rss/articles/CBMidEFVX3lxTE1qTDdIQkJ6WVpDbEFqN2J5ZllKVGhfMEdzeXBON2FNbkRkYTUxdUJMUlZpd2ZqV0djYXZIbzN6OHVmcDh1X0xmeGppNmhuWmJhanlORzluWjdKNDZoNTk1QWtGSVZOUldsdEljaFRNdjd4T0c1?oc=5",
          "press": ""
        }
      ],
      "related_titles": [
        "[배학수의 문화풍경] 도그마의 몰락"
      ],
      "category": "몰락"
    }
  ]
}