{
  "date": "2026-06-02",
  "hour": "16",
  "slot": "2026-06-02_16",
  "crawled_at": "2026-06-02 16:00:03",
  "total_articles": 409,
  "topics": [
    {
      "rank": 1,
      "keyword": "젠슨",
      "count": 36,
      "representative_title": "“반도체 넘어 로봇” 젠슨 황 한국에 베팅하나",
      "representative_link": "https://n.news.naver.com/article/050/0000106866?ntype=RANKING",
      "press": "한경비즈니스",
      "related_articles": [
        {
          "title": "\"한국 투자 검토\" 젠슨 황 발언에 들썩…'분야'도 꼽았다",
          "link": "https://n.news.naver.com/article/055/0001361034?ntype=RANKING",
          "press": "SBS"
        },
        {
          "title": "AI, 로봇… 젠슨 황 방한이 몰고 올 '포스트 반도체' 바람&#160;",
          "link": "https://n.news.naver.com/article/665/0000007482?ntype=RANKING",
          "press": "더스쿠프"
        },
        {
          "title": "韓 성과급 논란에 젠슨 황 “가급적 많은 보상해야”",
          "link": "https://n.news.naver.com/article/011/0004626948?ntype=RANKING",
          "press": "서울경제"
        },
        {
          "title": "\"삼성 6억 성과급 괜찮냐\" 질문에…젠슨 황 의외 답변 '술렁'",
          "link": "https://n.news.naver.com/article/088/0001012693?ntype=RANKING",
          "press": "매일신문"
        },
        {
          "title": "[단독] 젠슨 황, 하닉 옆 앉고 LG와 포옹…대만식 치맥으로 ‘제2 깐부 회동’",
          "link": "https://n.news.naver.com/article/009/0005688167?ntype=RANKING",
          "press": "매일경제"
        }
      ],
      "related_titles": [
        "\"한국 투자 검토\" 젠슨 황 발언에 들썩…'분야'도 꼽았다",
        "AI, 로봇… 젠슨 황 방한이 몰고 올 '포스트 반도체' 바람&#160;",
        "韓 성과급 논란에 젠슨 황 “가급적 많은 보상해야”",
        "\"삼성 6억 성과급 괜찮냐\" 질문에…젠슨 황 의외 답변 '술렁'",
        "[단독] 젠슨 황, 하닉 옆 앉고 LG와 포옹…대만식 치맥으로 ‘제2 깐부 회동’"
      ],
      "category": "경제/투자"
    },
    {
      "rank": 2,
      "keyword": "대통령",
      "count": 25,
      "representative_title": "이 대통령, 검찰에 \"무오류의 함정 빠지면 안 돼\"",
      "representative_link": "https://n.news.naver.com/article/047/0002518022?ntype=RANKING",
      "press": "오마이뉴스",
      "related_articles": [
        {
          "title": "김준일 \"감옥 간 尹 빼곤 전직 대통령 다 돌아다녀…文 '좋아요'는 양반\"[한칼토론]",
          "link": "https://n.news.naver.com/article/079/0004153172?ntype=RANKING",
          "press": "노컷뉴스"
        },
        {
          "title": "이 대통령, 검찰에 \"무오류의 함정 빠지면 안 돼\"",
          "link": "https://n.news.naver.com/article/047/0002518022?ntype=RANKING",
          "press": "오마이뉴스"
        },
        {
          "title": "이 대통령 \"마약사범들, 돈 쓰면서 교도소 가지 말고 일찍 치료 받으라\"",
          "link": "https://n.news.naver.com/article/437/0000494065?ntype=RANKING",
          "press": "JTBC"
        },
        {
          "title": "[속보]이 대통령, 한화에어로 폭발 사고에 “동일 사고 반복 발생…심각한 문제”",
          "link": "https://n.news.naver.com/article/032/0003449382?ntype=RANKING",
          "press": "경향신문"
        },
        {
          "title": "이 대통령, 검찰에 “잘못하면 사과·취소해야…무오류 함정 안 돼”",
          "link": "https://n.news.naver.com/article/028/0002807743?ntype=RANKING",
          "press": "한겨레"
        }
      ],
      "related_titles": [
        "김준일 \"감옥 간 尹 빼곤 전직 대통령 다 돌아다녀…文 '좋아요'는 양반\"[한칼토론]",
        "이 대통령, 검찰에 \"무오류의 함정 빠지면 안 돼\"",
        "이 대통령 \"마약사범들, 돈 쓰면서 교도소 가지 말고 일찍 치료 받으라\"",
        "[속보]이 대통령, 한화에어로 폭발 사고에 “동일 사고 반복 발생…심각한 문제”",
        "이 대통령, 검찰에 “잘못하면 사과·취소해야…무오류 함정 안 돼”"
      ],
      "category": "사건/사고"
    },
    {
      "rank": 3,
      "keyword": "삼성전자",
      "count": 22,
      "representative_title": "[속보]삼성전자, 글로벌 시총 ‘톱10’ 진입…메타 제쳐",
      "representative_link": "https://n.news.naver.com/article/021/0002795103?ntype=RANKING",
      "press": "문화일보",
      "related_articles": [
        {
          "title": "[속보]삼성전자, 글로벌 시총 ‘톱10’ 진입…메타 제쳐",
          "link": "https://n.news.naver.com/article/021/0002795103?ntype=RANKING",
          "press": "문화일보"
        },
        {
          "title": "삼성전자, 베트남 최초 DPPA 체결...세계 최대 스마트폰 공장에 재생에너지 쓴다",
          "link": "https://n.news.naver.com/article/030/0003433702?ntype=RANKING",
          "press": "전자신문"
        },
        {
          "title": "[단독] 삼성전자 미국 법인, 9월부터 이전‥\"인력 감축은 무관\"",
          "link": "https://n.news.naver.com/article/214/0001502729?ntype=RANKING",
          "press": "MBC"
        },
        {
          "title": "[컴퓨텍스2026] 삼성전자, HBM5 첫 공개…송재혁 CTO \"IDM 강점으로 승부\"",
          "link": "https://n.news.naver.com/article/293/0000085677?ntype=RANKING",
          "press": "블로터"
        },
        {
          "title": "“애플 3배 넘는 삼성전자 보상…획일적 성과급 개편해야”",
          "link": "https://n.news.naver.com/article/018/0006296054?ntype=RANKING",
          "press": "이데일리"
        }
      ],
      "related_titles": [
        "[속보]삼성전자, 글로벌 시총 ‘톱10’ 진입…메타 제쳐",
        "삼성전자, 베트남 최초 DPPA 체결...세계 최대 스마트폰 공장에 재생에너지 쓴다",
        "[단독] 삼성전자 미국 법인, 9월부터 이전‥\"인력 감축은 무관\"",
        "[컴퓨텍스2026] 삼성전자, HBM5 첫 공개…송재혁 CTO \"IDM 강점으로 승부\"",
        "“애플 3배 넘는 삼성전자 보상…획일적 성과급 개편해야”"
      ],
      "category": "산업/테크"
    },
    {
      "rank": 4,
      "keyword": "여고생",
      "count": 12,
      "representative_title": "베트남 여성에 벌인 수법이었다…여고생 저항하자 결국",
      "representative_link": "https://n.news.naver.com/article/055/0001361098?ntype=RANKING",
      "press": "SBS",
      "related_articles": [
        {
          "title": "[속보]성범죄 목적 드러난 여고생 살해범 장윤기 구속기소…불법촬영 혐의 추가",
          "link": "https://n.news.naver.com/article/079/0004153332?ntype=RANKING",
          "press": "노컷뉴스"
        },
        {
          "title": "베트남 여성에 벌인 수법이었다…여고생 저항하자 결국",
          "link": "https://n.news.naver.com/article/055/0001361098?ntype=RANKING",
          "press": "SBS"
        },
        {
          "title": "'광주 여고생 살해' 장윤기, 성폭행 의도로 접근 사실 드러나",
          "link": "https://n.news.naver.com/article/052/0002361096?ntype=RANKING",
          "press": "YTN"
        },
        {
          "title": "“광주 여고생 성폭행하려다 살해” 檢, 장윤기 ‘강간 등 살인’ 혐의 구속기소",
          "link": "https://n.news.naver.com/article/081/0003648961?ntype=RANKING",
          "press": "서울신문"
        },
        {
          "title": "17세 여고생 살해 장윤기, 성폭행 하려다 저항하자 범행",
          "link": "https://n.news.naver.com/article/449/0000347527?ntype=RANKING",
          "press": "채널A"
        }
      ],
      "related_titles": [
        "[속보]성범죄 목적 드러난 여고생 살해범 장윤기 구속기소…불법촬영 혐의 추가",
        "베트남 여성에 벌인 수법이었다…여고생 저항하자 결국",
        "'광주 여고생 살해' 장윤기, 성폭행 의도로 접근 사실 드러나",
        "“광주 여고생 성폭행하려다 살해” 檢, 장윤기 ‘강간 등 살인’ 혐의 구속기소",
        "17세 여고생 살해 장윤기, 성폭행 하려다 저항하자 범행"
      ],
      "category": "사회/일반"
    },
    {
      "rank": 5,
      "keyword": "싸이",
      "count": 12,
      "representative_title": "'수면제 대리수령' 싸이 검찰 송치…의료법 위반 혐의",
      "representative_link": "https://n.news.naver.com/article/422/0000870631?ntype=RANKING",
      "press": "연합뉴스TV",
      "related_articles": [
        {
          "title": "'흠뻑쇼' 앞둔 싸이, '수면제 대리 수령' 혐의로 검찰 송치",
          "link": "https://n.news.naver.com/article/079/0004153220?ntype=RANKING",
          "press": "노컷뉴스"
        },
        {
          "title": "싸이 '수면제 대리수령'으로 불구속 송치…의료법 위반 혐의(종합)",
          "link": "https://n.news.naver.com/article/001/0016113949?ntype=RANKING",
          "press": "연합뉴스"
        },
        {
          "title": "[단독] '약물 비대면 처방·대리수령' 싸이 등 6명 송치",
          "link": "https://n.news.naver.com/article/214/0001502722?ntype=RANKING",
          "press": "MBC"
        },
        {
          "title": "[단독] “담당교수 자리 비우자 후배가 대신 처방”…싸이·세브란스 의사 등 6명 검찰 송치",
          "link": "https://n.news.naver.com/article/056/0012192374?ntype=RANKING",
          "press": "KBS"
        },
        {
          "title": "'수면제 대리수령' 싸이 검찰 송치…의료법 위반 혐의",
          "link": "https://n.news.naver.com/article/422/0000870631?ntype=RANKING",
          "press": "연합뉴스TV"
        }
      ],
      "related_titles": [
        "'흠뻑쇼' 앞둔 싸이, '수면제 대리 수령' 혐의로 검찰 송치",
        "싸이 '수면제 대리수령'으로 불구속 송치…의료법 위반 혐의(종합)",
        "[단독] '약물 비대면 처방·대리수령' 싸이 등 6명 송치",
        "[단독] “담당교수 자리 비우자 후배가 대신 처방”…싸이·세브란스 의사 등 6명 검찰 송치",
        "'수면제 대리수령' 싸이 검찰 송치…의료법 위반 혐의"
      ],
      "category": "건강/의료"
    }
  ],
  "stock_topics": [
    {
      "rank": 1,
      "keyword": "삼성전자",
      "count": 22,
      "representative_title": "젠슨 황, 삼성전자 성과급 질문에 \"가능한 많이…\"",
      "representative_link": "https://n.news.naver.com/article/119/0003097036?ntype=RANKING",
      "press": "데일리안",
      "related_articles": [
        {
          "title": "젠슨 황, 삼성전자 성과급 질문에...\"가능한 한 많이 보상해야\"",
          "link": "https://n.news.naver.com/article/052/0002361053?ntype=RANKING",
          "press": "YTN"
        },
        {
          "title": "젠슨 황, 삼성전자 성과급 관련 질문에 \"가능한 한 많은 보수 줘야\"",
          "link": "https://n.news.naver.com/article/422/0000870648?ntype=RANKING",
          "press": "연합뉴스TV"
        },
        {
          "title": "[단독] 삼성전자 미국 법인, 9월부터 이전‥\"인력 감축은 무관\"",
          "link": "https://n.news.naver.com/article/214/0001502729?ntype=RANKING",
          "press": "MBC"
        },
        {
          "title": "젠슨 황, 삼성전자 질문에 \"가능한 한 많은 성과급 보상해야\"",
          "link": "https://n.news.naver.com/article/001/0016113760?ntype=RANKING",
          "press": "연합뉴스"
        },
        {
          "title": "삼성전자, 장중 글로벌 시총 9위 등극…“85만전자까지 간다”",
          "link": "https://n.news.naver.com/article/016/0002651194?ntype=RANKING",
          "press": "헤럴드경제"
        }
      ],
      "related_titles": [
        "젠슨 황, 삼성전자 성과급 질문에...\"가능한 한 많이 보상해야\"",
        "젠슨 황, 삼성전자 성과급 관련 질문에 \"가능한 한 많은 보수 줘야\"",
        "[단독] 삼성전자 미국 법인, 9월부터 이전‥\"인력 감축은 무관\"",
        "젠슨 황, 삼성전자 질문에 \"가능한 한 많은 성과급 보상해야\"",
        "삼성전자, 장중 글로벌 시총 9위 등극…“85만전자까지 간다”"
      ],
      "category": "주식/코인"
    },
    {
      "rank": 2,
      "keyword": "젠슨",
      "count": 15,
      "representative_title": "'젠슨 황 효과'에 LG전자 연일 급등…LG그룹주 들썩",
      "representative_link": "https://n.news.naver.com/article/243/0000098581?ntype=RANKING",
      "press": "이코노미스트",
      "related_articles": [
        {
          "title": "젠슨 황 \"한국 로보틱스 투자 검토...GTC 서울 개최도 가능\"",
          "link": "https://n.news.naver.com/article/660/0000110448?ntype=RANKING",
          "press": "kbc광주방송"
        },
        {
          "title": "\"한국 투자 검토\" 젠슨 황 발언에 들썩…'분야'도 꼽았다",
          "link": "https://n.news.naver.com/article/055/0001361034?ntype=RANKING",
          "press": "SBS"
        },
        {
          "title": "\"로봇만 살아남았다\"…젠슨 황 방한 소식에 상한가 달리던 LG·두산 일제히 급락",
          "link": "https://n.news.naver.com/article/082/0001383442?ntype=RANKING",
          "press": "부산일보"
        },
        {
          "title": "\"젠슨 황 로봇 시구 하나요?\"…\"투자 검토\" 콕 찍자 29%↑ 확 뛰었다",
          "link": "https://n.news.naver.com/article/215/0001254100?ntype=RANKING",
          "press": "한국경제TV"
        },
        {
          "title": "“젠슨 황 덕분에 또?”…LG전자 상한가 ‘불기둥’ [오늘, 이 종목]",
          "link": "https://n.news.naver.com/article/024/0000105939?ntype=RANKING",
          "press": "매경이코노미"
        }
      ],
      "related_titles": [
        "젠슨 황 \"한국 로보틱스 투자 검토...GTC 서울 개최도 가능\"",
        "\"한국 투자 검토\" 젠슨 황 발언에 들썩…'분야'도 꼽았다",
        "\"로봇만 살아남았다\"…젠슨 황 방한 소식에 상한가 달리던 LG·두산 일제히 급락",
        "\"젠슨 황 로봇 시구 하나요?\"…\"투자 검토\" 콕 찍자 29%↑ 확 뛰었다",
        "“젠슨 황 덕분에 또?”…LG전자 상한가 ‘불기둥’ [오늘, 이 종목]"
      ],
      "category": "주식/코인"
    },
    {
      "rank": 3,
      "keyword": "시총",
      "count": 5,
      "representative_title": "반도체의 힘…韓증시 시총 인도 제치고 '세계 6위'",
      "representative_link": "https://n.news.naver.com/article/215/0001254089?ntype=RANKING",
      "press": "한국경제TV",
      "related_articles": [
        {
          "title": "삼전·하닉 견인에… 韓증시, 인도 제치고 세계 시총 6위로",
          "link": "https://n.news.naver.com/article/018/0006296084?ntype=RANKING",
          "press": "이데일리"
        },
        {
          "title": "반도체의 힘…韓증시 시총 인도 제치고 '세계 6위'",
          "link": "https://n.news.naver.com/article/215/0001254089?ntype=RANKING",
          "press": "한국경제TV"
        },
        {
          "title": "삼전·하닉 견인에… 韓증시, 인도 제치고 세계 시총 6위로",
          "link": "https://n.news.naver.com/article/018/0006296084?ntype=RANKING",
          "press": "이데일리"
        },
        {
          "title": "반도체의 힘…韓증시 시총 인도 제치고 '세계 6위'",
          "link": "https://n.news.naver.com/article/215/0001254089?ntype=RANKING",
          "press": "한국경제TV"
        },
        {
          "title": "삼전·하닉 견인에… 韓증시, 인도 제치고 세계 시총 6위로",
          "link": "https://n.news.naver.com/article/018/0006296084?ntype=RANKING",
          "press": "이데일리"
        }
      ],
      "related_titles": [
        "삼전·하닉 견인에… 韓증시, 인도 제치고 세계 시총 6위로",
        "반도체의 힘…韓증시 시총 인도 제치고 '세계 6위'",
        "삼전·하닉 견인에… 韓증시, 인도 제치고 세계 시총 6위로",
        "반도체의 힘…韓증시 시총 인도 제치고 '세계 6위'",
        "삼전·하닉 견인에… 韓증시, 인도 제치고 세계 시총 6위로"
      ],
      "category": "주식/코인"
    },
    {
      "rank": 4,
      "keyword": "투자",
      "count": 5,
      "representative_title": "소유 \"10년 전 '삼전닉스'에 1억 투자\"…최근 수익 근황 공개",
      "representative_link": "https://n.news.naver.com/article/215/0001254037?ntype=RANKING",
      "press": "한국경제TV",
      "related_articles": [
        {
          "title": "소유 \"10년 전 '삼전닉스'에 1억 투자\"…최근 수익 근황 공개",
          "link": "https://n.news.naver.com/article/215/0001254037?ntype=RANKING",
          "press": "한국경제TV"
        },
        {
          "title": "우나스텔라, 335억원 투자 받았다…\"유인 우주비행 로켓 개발 박차\"",
          "link": "https://n.news.naver.com/article/584/0000037867?ntype=RANKING",
          "press": "동아사이언스"
        },
        {
          "title": "소유 \"10년 전 '삼전닉스'에 1억 투자\"…최근 수익 근황 공개",
          "link": "https://n.news.naver.com/article/215/0001254037?ntype=RANKING",
          "press": "한국경제TV"
        },
        {
          "title": "우나스텔라, 335억원 투자 받았다…\"유인 우주비행 로켓 개발 박차\"",
          "link": "https://n.news.naver.com/article/584/0000037867?ntype=RANKING",
          "press": "동아사이언스"
        },
        {
          "title": "소유 \"10년 전 '삼전닉스'에 1억 투자\"…최근 수익 근황 공개",
          "link": "https://n.news.naver.com/article/215/0001254037?ntype=RANKING",
          "press": "한국경제TV"
        }
      ],
      "related_titles": [
        "소유 \"10년 전 '삼전닉스'에 1억 투자\"…최근 수익 근황 공개",
        "우나스텔라, 335억원 투자 받았다…\"유인 우주비행 로켓 개발 박차\"",
        "소유 \"10년 전 '삼전닉스'에 1억 투자\"…최근 수익 근황 공개",
        "우나스텔라, 335억원 투자 받았다…\"유인 우주비행 로켓 개발 박차\"",
        "소유 \"10년 전 '삼전닉스'에 1억 투자\"…최근 수익 근황 공개"
      ],
      "category": "주식/코인"
    },
    {
      "rank": 5,
      "keyword": "전자",
      "count": 4,
      "representative_title": "상한가 뒤 급락한 LG전자…엔비디아 협력 기대감은 '현재진행형'",
      "representative_link": "https://n.news.naver.com/article/629/0000504302?ntype=RANKING",
      "press": "더팩트",
      "related_articles": [
        {
          "title": "흔들리는 LG전자·네이버, 고수들은 담았다 [주식 초고수는 지금]",
          "link": "https://n.news.naver.com/article/011/0004626953?ntype=RANKING",
          "press": "서울경제"
        },
        {
          "title": "상한가 뒤 급락한 LG전자…엔비디아 협력 기대감은 '현재진행형'",
          "link": "https://n.news.naver.com/article/629/0000504302?ntype=RANKING",
          "press": "더팩트"
        },
        {
          "title": "흔들리는 LG전자·네이버, 고수들은 담았다 [주식 초고수는 지금]",
          "link": "https://n.news.naver.com/article/011/0004626953?ntype=RANKING",
          "press": "서울경제"
        },
        {
          "title": "상한가 뒤 급락한 LG전자…엔비디아 협력 기대감은 '현재진행형'",
          "link": "https://n.news.naver.com/article/629/0000504302?ntype=RANKING",
          "press": "더팩트"
        },
        {
          "title": "흔들리는 LG전자·네이버, 고수들은 담았다 [주식 초고수는 지금]",
          "link": "https://n.news.naver.com/article/011/0004626953?ntype=RANKING",
          "press": "서울경제"
        }
      ],
      "related_titles": [
        "흔들리는 LG전자·네이버, 고수들은 담았다 [주식 초고수는 지금]",
        "상한가 뒤 급락한 LG전자…엔비디아 협력 기대감은 '현재진행형'",
        "흔들리는 LG전자·네이버, 고수들은 담았다 [주식 초고수는 지금]",
        "상한가 뒤 급락한 LG전자…엔비디아 협력 기대감은 '현재진행형'",
        "흔들리는 LG전자·네이버, 고수들은 담았다 [주식 초고수는 지금]"
      ],
      "category": "주식/코인"
    }
  ],
  "moljak_topics": [
    {
      "rank": 1,
      "keyword": "소림사",
      "series_title": "소림사의 몰락",
      "count": 2,
      "representative_title": "소림사의 몰락…‘쿵푸’ 띄운 전 주지, 668억 횡령으로 징역 24년",
      "representative_link": "https://news.google.com/rss/articles/CBMiVkFVX3lxTE1IQS01QXhhM3l5b3kyTW9GcXZ6M0ZKUjhJV3c3cTZRZFV6SFlSVlh0M2QweGdpM2lXQVRjbGhvVU1LV3JxOWVnZ3NXNl8xZ09iSGhzaEJn?oc=5",
      "press": "",
      "related_articles": [
        {
          "title": "소림사의 몰락…‘쿵푸’ 띄운 전 주지, 668억 횡령으로 징역 24년",
          "link": "https://news.google.com/rss/articles/CBMiVkFVX3lxTE1IQS01QXhhM3l5b3kyTW9GcXZ6M0ZKUjhJV3c3cTZRZFV6SFlSVlh0M2QweGdpM2lXQVRjbGhvVU1LV3JxOWVnZ3NXNl8xZ09iSGhzaEJn?oc=5",
          "press": ""
        },
        {
          "title": "‘소림사의 몰락’… 30년간 600억대 횡령한 전 주지 징역 24년 중형",
          "link": "https://news.google.com/rss/articles/CBMiVEFVX3lxTFAzeW1QdF90ckNwaGFJNFREUlNRQktYUDZ2VWw1UUdMTi1FM2VLZE83R1NsRGF2djhZZkllRXpqcHA2NFludkNxeHQ2Wmx2bVhmZGRHYQ?oc=5",
          "press": ""
        }
      ],
      "related_titles": [
        "소림사의 몰락…‘쿵푸’ 띄운 전 주지, 668억 횡령으로 징역 24년",
        "‘소림사의 몰락’… 30년간 600억대 횡령한 전 주지 징역 24년 중형"
      ],
      "category": "몰락"
    },
    {
      "rank": 2,
      "keyword": "ATM",
      "series_title": "ATM의 몰락",
      "count": 2,
      "representative_title": "비트코인 ATM의 몰락…편의성 잃고 규제에 막혔다",
      "representative_link": "https://news.google.com/rss/articles/CBMiaEFVX3lxTE5xOV9uOFRlQUVNOFJoenJKdjU0MExmUUVtSGx3TzE1QXU0Q19MSV92OEs5c2hOc3BBbDI2R054djRQS1FzVzlMalRFd1FXbU1TTmFUeUd2UGlWSkZRXzI1UTlsVXFVSlhu?oc=5",
      "press": "",
      "related_articles": [
        {
          "title": "비트코인 ATM의 몰락…편의성 잃고 규제에 막혔다",
          "link": "https://news.google.com/rss/articles/CBMiaEFVX3lxTE5xOV9uOFRlQUVNOFJoenJKdjU0MExmUUVtSGx3TzE1QXU0Q19MSV92OEs5c2hOc3BBbDI2R054djRQS1FzVzlMalRFd1FXbU1TTmFUeUd2UGlWSkZRXzI1UTlsVXFVSlhu?oc=5",
          "press": ""
        },
        {
          "title": "비트코인 ATM의 몰락, 북미 최대 사업자 파산이 던진 경고",
          "link": "https://news.google.com/rss/articles/CBMiZ0FVX3lxTE81LWpwaEhsdHA3Zzd1YUxwaVpOaEJnTUV4X0t3Z2xpVF9uQTFwUkh2TzlleVJzemVlN19RaFNRd090NFA4WnJfRmdVM3pmZGhraUwtV0tYLThxTWZ5am40dFBxVFk1Wm_SAWtBVV95cUxQZFE3QVNOcnF5UDhkS2N4RzEtNjRuRTJsVnMybUNXNEtEOWFNSkZUN2tvYkRsNjV0UXFjSUJxY2ZzUDNxQU9QWDJsMFROMWZYbE93STRwLW5sV01waXV5ZUZqMkJJaVJzRFprSQ?oc=5",
          "press": ""
        }
      ],
      "related_titles": [
        "비트코인 ATM의 몰락…편의성 잃고 규제에 막혔다",
        "비트코인 ATM의 몰락, 북미 최대 사업자 파산이 던진 경고"
      ],
      "category": "몰락"
    },
    {
      "rank": 3,
      "keyword": "비참한",
      "series_title": "비참한의 몰락",
      "count": 1,
      "representative_title": "‘CEO 승려’의 비참한 몰락… 中 소림사 전 주지, 600억대 횡령·뇌물로 징역 24년 중형",
      "representative_link": "https://news.google.com/rss/articles/CBMiakFVX3lxTE1LcjBIS3BvTk9MRGdneGFaQlZYSmh6SEpZYnpBTHU2OXZJbXBzekZkRGZaS1FoaEtOOGdDWmd5bXRXUzEzQngwMFoxc2F4aEl5T3BLbTJXSGxDdFEzUndOVU9wUTU2Y0thLXfSAW5BVV95cUxQbjJ4RFEzNW50MmZ5QkJyalZzZzY1YmZxS3FRRVRCR2kybGxVNVFDaG1BMFgxMTZHT0oyVm42Zmt4MWtxckRjTEsxVVVtQTk4U2U2MmF1REljaUdPUnZwbmx0TFV6d1dXYk5WQlJuZw?oc=5",
      "press": "",
      "related_articles": [
        {
          "title": "‘CEO 승려’의 비참한 몰락… 中 소림사 전 주지, 600억대 횡령·뇌물로 징역 24년 중형",
          "link": "https://news.google.com/rss/articles/CBMiakFVX3lxTE1LcjBIS3BvTk9MRGdneGFaQlZYSmh6SEpZYnpBTHU2OXZJbXBzekZkRGZaS1FoaEtOOGdDWmd5bXRXUzEzQngwMFoxc2F4aEl5T3BLbTJXSGxDdFEzUndOVU9wUTU2Y0thLXfSAW5BVV95cUxQbjJ4RFEzNW50MmZ5QkJyalZzZzY1YmZxS3FRRVRCR2kybGxVNVFDaG1BMFgxMTZHT0oyVm42Zmt4MWtxckRjTEsxVVVtQTk4U2U2MmF1REljaUdPUnZwbmx0TFV6d1dXYk5WQlJuZw?oc=5",
          "press": ""
        }
      ],
      "related_titles": [
        "‘CEO 승려’의 비참한 몰락… 中 소림사 전 주지, 600억대 횡령·뇌물로 징역 24년 중형"
      ],
      "category": "몰락"
    },
    {
      "rank": 4,
      "keyword": "승려",
      "series_title": "승려의 몰락",
      "count": 1,
      "representative_title": "애인 7명, 자녀 21명? 논란된 'CEO 승려' 몰락...668억 횡령까지 - 머니투데이",
      "representative_link": "https://news.google.com/rss/articles/CBMia0FVX3lxTFBrbnNvZFo1dThqcEpXM1pLMjdwNXB4ckQ3aHNOZmIweXItOXNTc25EYlRXcU1SWE9UUkhlU010MG4tblNMVkJlVTdnZ21WaTE4WDB1OU9YV3Zxd3dJbklfZktxWEp0RWFkSlpz0gFwQVVfeXFMTkx2UjBsTF9lTVozRy00U0R5NHJGR1FpZkV6R2doU3F4REVXT2NTcTBpbXhvR3FHejREc3pZb2hZX2h1WVlyaW1LNXo2dXFEWHVpazhHVVo4dUxyT21jd1Q0clpTODF1eWdOMDNpdlo1VA?oc=5",
      "press": "",
      "related_articles": [
        {
          "title": "애인 7명, 자녀 21명? 논란된 'CEO 승려' 몰락...668억 횡령까지 - 머니투데이",
          "link": "https://news.google.com/rss/articles/CBMia0FVX3lxTFBrbnNvZFo1dThqcEpXM1pLMjdwNXB4ckQ3aHNOZmIweXItOXNTc25EYlRXcU1SWE9UUkhlU010MG4tblNMVkJlVTdnZ21WaTE4WDB1OU9YV3Zxd3dJbklfZktxWEp0RWFkSlpz0gFwQVVfeXFMTkx2UjBsTF9lTVozRy00U0R5NHJGR1FpZkV6R2doU3F4REVXT2NTcTBpbXhvR3FHejREc3pZb2hZX2h1WVlyaW1LNXo2dXFEWHVpazhHVVo4dUxyT21jd1Q0clpTODF1eWdOMDNpdlo1VA?oc=5",
          "press": ""
        }
      ],
      "related_titles": [
        "애인 7명, 자녀 21명? 논란된 'CEO 승려' 몰락...668억 횡령까지 - 머니투데이"
      ],
      "category": "몰락"
    },
    {
      "rank": 5,
      "keyword": "보수",
      "series_title": "보수의 몰락",
      "count": 1,
      "representative_title": "[선택! 6.3]홍준표 \"사이비 보수가 보수 몰락 불러\" - the",
      "representative_link": "https://news.google.com/rss/articles/CBMia0FVX3lxTE5JSW00akFjNkRRMDJUVHFrMUxHd3YxMzBITW5fNUYtcW5EaWpPTEEyX1VrQnpyZ3JxaVAySHRDeW1NMmlWejNZY2VVU3FERU5QTnlOX2VFc3FmRDh6WUJFMk5WeEhKNWE1c2I4?oc=5",
      "press": "",
      "related_articles": [
        {
          "title": "[선택! 6.3]홍준표 \"사이비 보수가 보수 몰락 불러\" - the",
          "link": "https://news.google.com/rss/articles/CBMia0FVX3lxTE5JSW00akFjNkRRMDJUVHFrMUxHd3YxMzBITW5fNUYtcW5EaWpPTEEyX1VrQnpyZ3JxaVAySHRDeW1NMmlWejNZY2VVU3FERU5QTnlOX2VFc3FmRDh6WUJFMk5WeEhKNWE1c2I4?oc=5",
          "press": ""
        }
      ],
      "related_titles": [
        "[선택! 6.3]홍준표 \"사이비 보수가 보수 몰락 불러\" - the"
      ],
      "category": "몰락"
    }
  ]
}